pylgrum/__init__.py
pylgrum/card.py
pylgrum/deck.py
pylgrum/errors.py
pylgrum/game.py
pylgrum/hand.py
pylgrum/meld.py
pylgrum/move.py
pylgrum/player.py
pylgrum/stack.py
pylgrum/server/__init__.py
pylgrum/server/contestant.py
pylgrum/server/errors.py
pylgrum/server/game_manager.py
pylgrum/server/tests/__init__.py
pylgrum/server/tests/test_game_manager.py
pylgrum/tests/__init__.py
pylgrum/tests/test_card.py
pylgrum/tests/test_deck.py
pylgrum/tests/test_game.py
pylgrum/tests/test_hand.py
pylgrum/tests/test_meld.py
pylgrum/tests/test_move.py
pylgrum/tests/test_player.py
pylgrum/tests/test_stack.py
pylgrum/tui/__init__.py
pylgrum/tui/game.py
pylgrum/tui/hand_melds.py
pylgrum/tui/player.py
pylgrum/tui/util.py
pylgrum-0.0.1.dist-info/LICENSE
pylgrum-0.0.1.dist-info/METADATA
pylgrum-0.0.1.dist-info/WHEEL
pylgrum-0.0.1.dist-info/top_level.txt
pylgrum-0.0.1.dist-info/RECORD
