Metadata-Version: 2.1
Name: pylgrum
Version: 0.0.1
Summary: A library for modeling and playing the card game Gin Rummy
Home-page: https://github.com/jrheling/pylgrum
Author: Joshua R. Heling
Author-email: jrh-pypi@netfluvia.org
License: UNKNOWN
Platform: UNKNOWN
Classifier: Programming Language :: Python :: 3
Classifier: License :: OSI Approved :: MIT License
Classifier: Operating System :: OS Independent
Classifier: Development Status :: 2 - Pre-Alpha
Classifier: Intended Audience :: Developers
Classifier: Topic :: Games/Entertainment
Requires-Python: >=3.6
